temprl/StructOutput.py
temprl/WebScrapper.py
temprl/__init__.py
temprl/htmlutils.py
temprl_pro-0.0.1b0.dist-info/METADATA
temprl_pro-0.0.1b0.dist-info/WHEEL
temprl_pro-0.0.1b0.dist-info/entry_points.txt
temprl_pro-0.0.1b0.dist-info/top_level.txt
temprl_pro-0.0.1b0.dist-info/RECORD
