Metadata-Version: 2.1
Name: temprl-pro
Version: 0.0.1b0
Home-page: https://github.com/Pr0fe5s0r
Author: Sri Santh M
Author-email: srisanth234567@gmail.com
License: MIT
Requires-Dist: selenium
Requires-Dist: html2text
